CustomCam/__init__.py
CustomCam/__main__.py
CustomCam/camera.py
CustomCam/filters.py
CustomCam/utils.py
CustomCam-0.0.2.dist-info/LICENSE
CustomCam-0.0.2.dist-info/METADATA
CustomCam-0.0.2.dist-info/WHEEL
CustomCam-0.0.2.dist-info/entry_points.txt
CustomCam-0.0.2.dist-info/top_level.txt
CustomCam-0.0.2.dist-info/RECORD
