Metadata-Version: 2.1
Name: CustomCam
Version: 0.0.2
Summary: Extendable webcam customisation in Python.
Home-page: https://github.com/mattravenhall/CustomCam
Author: Matt Ravenhall
License: UNKNOWN
Platform: UNKNOWN
Classifier: Development Status :: 4 - Beta
Classifier: Environment :: Console
Classifier: Natural Language :: English
Classifier: Operating System :: POSIX :: Linux
Classifier: Operating System :: Microsoft :: Windows
Classifier: Operating System :: MacOS :: MacOS X
Classifier: Programming Language :: Python :: 3
Classifier: Topic :: Multimedia :: Video
Requires-Python: >=3.7
License-File: LICENSE
Requires-Dist: mediapipe
Requires-Dist: numpy
Requires-Dist: opencv-python
Requires-Dist: pyvirtualcam
